misteravif.py
misteravif-1.0.0.dist-info/LICENSE
misteravif-1.0.0.dist-info/METADATA
misteravif-1.0.0.dist-info/WHEEL
misteravif-1.0.0.dist-info/entry_points.txt
misteravif-1.0.0.dist-info/RECORD
