Metadata-Version: 2.1
Name: misteravif
Version: 1.0.0
Summary: A tool to recompress images to AVIF to determine desired compression quality
Home-page: https://github.com/ulikoehler/MisterAVIF
License: MIT
Keywords: avif,image,compression,quality,analysis
Author: MisterAVIF Contributors
Requires-Python: >=3.8,<4.0
Classifier: Development Status :: 4 - Beta
Classifier: Intended Audience :: Developers
Classifier: License :: OSI Approved :: MIT License
Classifier: Operating System :: OS Independent
Classifier: Programming Language :: Python :: 3
Classifier: Programming Language :: Python :: 3.8
Classifier: Programming Language :: Python :: 3.9
Classifier: Programming Language :: Python :: 3.10
Classifier: Programming Language :: Python :: 3.11
Classifier: Programming Language :: Python :: 3.12
Classifier: Programming Language :: Python :: 3.13
Classifier: Topic :: Multimedia :: Graphics :: Graphics Conversion
Classifier: Topic :: Software Development :: Libraries :: Python Modules
Requires-Dist: Pillow (>=8.0.0,<9.0.0)
Requires-Dist: matplotlib (>=3.5.0,<4.0.0)
Requires-Dist: numpy (>=1.20.0,<2.0.0)
Requires-Dist: pillow-avif-plugin (>=1.4.0,<2.0.0)
Requires-Dist: tqdm (>=4.60.0,<5.0.0)
Project-URL: Documentation, https://github.com/ulikoehler/MisterAVIF
Project-URL: Repository, https://github.com/ulikoehler/MisterAVIF
